light_famd/__init__.py
light_famd/ca.py
light_famd/famd.py
light_famd/mca.py
light_famd/mfa.py
light_famd/one_hot.py
light_famd/pca.py
light_famd/svd.py
light_famd/util.py
light_famd-0.0.3.dist-info/METADATA
light_famd-0.0.3.dist-info/WHEEL
light_famd-0.0.3.dist-info/top_level.txt
light_famd-0.0.3.dist-info/RECORD
