Metadata-Version: 2.1
Name: light-famd
Version: 0.0.3
Summary: Light Factor Analysis of Mixed Data
Home-page: https://github.com/Cauchemare/Light_FAMD
Author: telescopes
Author-email: luyaoli88@gmail.com
License: UNKNOWN
Keywords: famd,factor analysis
Platform: UNKNOWN
Classifier: Development Status :: 3 - Alpha
Classifier: Programming Language :: Python :: 3
Classifier: License :: OSI Approved :: BSD License 
Classifier: Operating System :: OS Independent
Classifier: Topic :: Scientific/Engineering :: Mathematics
Classifier: Topic :: Software Development :: Libraries :: Python Modules
Classifier: Intended Audience :: Science/Research
Requires-Dist: scikit-learn
Requires-Dist: scipy
Requires-Dist: pandas
Requires-Dist: numpy
